{"nodes": [{"id": "c_syncdash_src_lib_functions_product_attributes_ts", "label": "product-attributes.ts", "file_type": "code", "source_file": "C:\\syncdash\\src\\lib\\functions\\product-attributes.ts", "source_location": "L1"}, {"id": "functions_product_attributes_normalizenamespace", "label": "normalizeNamespace()", "file_type": "code", "source_file": "C:\\syncdash\\src\\lib\\functions\\product-attributes.ts", "source_location": "L21"}, {"id": "functions_product_attributes_normalizekey", "label": "normalizeKey()", "file_type": "code", "source_file": "C:\\syncdash\\src\\lib\\functions\\product-attributes.ts", "source_location": "L25"}, {"id": "functions_product_attributes_pairkey", "label": "pairKey()", "file_type": "code", "source_file": "C:\\syncdash\\src\\lib\\functions\\product-attributes.ts", "source_location": "L29"}, {"id": "functions_product_attributes_getproductattributes", "label": "getProductAttributes()", "file_type": "code", "source_file": "C:\\syncdash\\src\\lib\\functions\\product-attributes.ts", "source_location": "L33"}, {"id": "functions_product_attributes_setproductattributes", "label": "setProductAttributes()", "file_type": "code", "source_file": "C:\\syncdash\\src\\lib\\functions\\product-attributes.ts", "source_location": "L39"}], "edges": [{"source": "c_syncdash_src_lib_functions_product_attributes_ts", "target": "drizzle_orm", "relation": "imports_from", "confidence": "EXTRACTED", "source_file": "C:\\syncdash\\src\\lib\\functions\\product-attributes.ts", "source_location": "L1", "weight": 1.0}, {"source": "c_syncdash_src_lib_functions_product_attributes_ts", "target": "c_syncdash_src_lib_db_client", "relation": "imports_from", "confidence": "EXTRACTED", "source_file": "C:\\syncdash\\src\\lib\\functions\\product-attributes.ts", "source_location": "L2", "weight": 1.0}, {"source": "c_syncdash_src_lib_functions_product_attributes_ts", "target": "c_syncdash_src_lib_db_schema", "relation": "imports_from", "confidence": "EXTRACTED", "source_file": "C:\\syncdash\\src\\lib\\functions\\product-attributes.ts", "source_location": "L3", "weight": 1.0}, {"source": "c_syncdash_src_lib_functions_product_attributes_ts", "target": "c_syncdash_src_lib_utils_id", "relation": "imports_from", "confidence": "EXTRACTED", "source_file": "C:\\syncdash\\src\\lib\\functions\\product-attributes.ts", "source_location": "L4", "weight": 1.0}, {"source": "c_syncdash_src_lib_functions_product_attributes_ts", "target": "c_syncdash_src_lib_functions_log", "relation": "imports_from", "confidence": "EXTRACTED", "source_file": "C:\\syncdash\\src\\lib\\functions\\product-attributes.ts", "source_location": "L5", "weight": 1.0}, {"source": "c_syncdash_src_lib_functions_product_attributes_ts", "target": "c_syncdash_src_types_platform", "relation": "imports_from", "confidence": "EXTRACTED", "source_file": "C:\\syncdash\\src\\lib\\functions\\product-attributes.ts", "source_location": "L6", "weight": 1.0}, {"source": "c_syncdash_src_lib_functions_product_attributes_ts", "target": "functions_product_attributes_normalizenamespace", "relation": "contains", "confidence": "EXTRACTED", "source_file": "C:\\syncdash\\src\\lib\\functions\\product-attributes.ts", "source_location": "L21", "weight": 1.0}, {"source": "c_syncdash_src_lib_functions_product_attributes_ts", "target": "functions_product_attributes_normalizekey", "relation": "contains", "confidence": "EXTRACTED", "source_file": "C:\\syncdash\\src\\lib\\functions\\product-attributes.ts", "source_location": "L25", "weight": 1.0}, {"source": "c_syncdash_src_lib_functions_product_attributes_ts", "target": "functions_product_attributes_pairkey", "relation": "contains", "confidence": "EXTRACTED", "source_file": "C:\\syncdash\\src\\lib\\functions\\product-attributes.ts", "source_location": "L29", "weight": 1.0}, {"source": "c_syncdash_src_lib_functions_product_attributes_ts", "target": "functions_product_attributes_getproductattributes", "relation": "contains", "confidence": "EXTRACTED", "source_file": "C:\\syncdash\\src\\lib\\functions\\product-attributes.ts", "source_location": "L33", "weight": 1.0}, {"source": "c_syncdash_src_lib_functions_product_attributes_ts", "target": "functions_product_attributes_setproductattributes", "relation": "contains", "confidence": "EXTRACTED", "source_file": "C:\\syncdash\\src\\lib\\functions\\product-attributes.ts", "source_location": "L39", "weight": 1.0}, {"source": "functions_product_attributes_setproductattributes", "target": "functions_product_attributes_pairkey", "relation": "calls", "confidence": "EXTRACTED", "source_file": "C:\\syncdash\\src\\lib\\functions\\product-attributes.ts", "source_location": "L59", "weight": 1.0}, {"source": "functions_product_attributes_setproductattributes", "target": "functions_product_attributes_normalizenamespace", "relation": "calls", "confidence": "EXTRACTED", "source_file": "C:\\syncdash\\src\\lib\\functions\\product-attributes.ts", "source_location": "L64", "weight": 1.0}, {"source": "functions_product_attributes_setproductattributes", "target": "functions_product_attributes_normalizekey", "relation": "calls", "confidence": "EXTRACTED", "source_file": "C:\\syncdash\\src\\lib\\functions\\product-attributes.ts", "source_location": "L65", "weight": 1.0}], "raw_calls": [{"caller_nid": "functions_product_attributes_normalizenamespace", "callee": "toLowerCase", "source_file": "C:\\syncdash\\src\\lib\\functions\\product-attributes.ts", "source_location": "L22"}, {"caller_nid": "functions_product_attributes_normalizenamespace", "callee": "trim", "source_file": "C:\\syncdash\\src\\lib\\functions\\product-attributes.ts", "source_location": "L22"}, {"caller_nid": "functions_product_attributes_normalizekey", "callee": "toLowerCase", "source_file": "C:\\syncdash\\src\\lib\\functions\\product-attributes.ts", "source_location": "L26"}, {"caller_nid": "functions_product_attributes_normalizekey", "callee": "trim", "source_file": "C:\\syncdash\\src\\lib\\functions\\product-attributes.ts", "source_location": "L26"}, {"caller_nid": "functions_product_attributes_getproductattributes", "callee": "findMany", "source_file": "C:\\syncdash\\src\\lib\\functions\\product-attributes.ts", "source_location": "L34"}, {"caller_nid": "functions_product_attributes_getproductattributes", "callee": "eq", "source_file": "C:\\syncdash\\src\\lib\\functions\\product-attributes.ts", "source_location": "L35"}, {"caller_nid": "functions_product_attributes_setproductattributes", "callee": "findFirst", "source_file": "C:\\syncdash\\src\\lib\\functions\\product-attributes.ts", "source_location": "L45"}, {"caller_nid": "functions_product_attributes_setproductattributes", "callee": "eq", "source_file": "C:\\syncdash\\src\\lib\\functions\\product-attributes.ts", "source_location": "L46"}, {"caller_nid": "functions_product_attributes_setproductattributes", "callee": "findMany", "source_file": "C:\\syncdash\\src\\lib\\functions\\product-attributes.ts", "source_location": "L53"}, {"caller_nid": "functions_product_attributes_setproductattributes", "callee": "eq", "source_file": "C:\\syncdash\\src\\lib\\functions\\product-attributes.ts", "source_location": "L54"}, {"caller_nid": "functions_product_attributes_setproductattributes", "callee": "set", "source_file": "C:\\syncdash\\src\\lib\\functions\\product-attributes.ts", "source_location": "L59"}, {"caller_nid": "functions_product_attributes_setproductattributes", "callee": "set", "source_file": "C:\\syncdash\\src\\lib\\functions\\product-attributes.ts", "source_location": "L66"}, {"caller_nid": "functions_product_attributes_setproductattributes", "callee": "where", "source_file": "C:\\syncdash\\src\\lib\\functions\\product-attributes.ts", "source_location": "L76"}, {"caller_nid": "functions_product_attributes_setproductattributes", "callee": "delete", "source_file": "C:\\syncdash\\src\\lib\\functions\\product-attributes.ts", "source_location": "L76"}, {"caller_nid": "functions_product_attributes_setproductattributes", "callee": "eq", "source_file": "C:\\syncdash\\src\\lib\\functions\\product-attributes.ts", "source_location": "L76"}, {"caller_nid": "functions_product_attributes_setproductattributes", "callee": "clear", "source_file": "C:\\syncdash\\src\\lib\\functions\\product-attributes.ts", "source_location": "L77"}, {"caller_nid": "functions_product_attributes_setproductattributes", "callee": "values", "source_file": "C:\\syncdash\\src\\lib\\functions\\product-attributes.ts", "source_location": "L81"}, {"caller_nid": "functions_product_attributes_setproductattributes", "callee": "get", "source_file": "C:\\syncdash\\src\\lib\\functions\\product-attributes.ts", "source_location": "L84"}, {"caller_nid": "functions_product_attributes_setproductattributes", "callee": "where", "source_file": "C:\\syncdash\\src\\lib\\functions\\product-attributes.ts", "source_location": "L87"}, {"caller_nid": "functions_product_attributes_setproductattributes", "callee": "set", "source_file": "C:\\syncdash\\src\\lib\\functions\\product-attributes.ts", "source_location": "L87"}, {"caller_nid": "functions_product_attributes_setproductattributes", "callee": "update", "source_file": "C:\\syncdash\\src\\lib\\functions\\product-attributes.ts", "source_location": "L87"}, {"caller_nid": "functions_product_attributes_setproductattributes", "callee": "eq", "source_file": "C:\\syncdash\\src\\lib\\functions\\product-attributes.ts", "source_location": "L92"}, {"caller_nid": "functions_product_attributes_setproductattributes", "callee": "values", "source_file": "C:\\syncdash\\src\\lib\\functions\\product-attributes.ts", "source_location": "L97"}, {"caller_nid": "functions_product_attributes_setproductattributes", "callee": "insert", "source_file": "C:\\syncdash\\src\\lib\\functions\\product-attributes.ts", "source_location": "L97"}, {"caller_nid": "functions_product_attributes_setproductattributes", "callee": "generateId", "source_file": "C:\\syncdash\\src\\lib\\functions\\product-attributes.ts", "source_location": "L98"}, {"caller_nid": "functions_product_attributes_setproductattributes", "callee": "toISOString", "source_file": "C:\\syncdash\\src\\lib\\functions\\product-attributes.ts", "source_location": "L104"}, {"caller_nid": "functions_product_attributes_setproductattributes", "callee": "logOperation", "source_file": "C:\\syncdash\\src\\lib\\functions\\product-attributes.ts", "source_location": "L109"}, {"caller_nid": "functions_product_attributes_setproductattributes", "callee": "logOperation", "source_file": "C:\\syncdash\\src\\lib\\functions\\product-attributes.ts", "source_location": "L118"}]}